MorphLink/ConnectedComponents.py
MorphLink/__init__.py
MorphLink/calculate_dis.py
MorphLink/cc_util.py
MorphLink/contour_util.py
MorphLink/convolve2D.py
MorphLink/extract_hancraft_features_util.py
MorphLink/illustrate_util.py
MorphLink/main_functions.py
MorphLink/mask_util.py
MorphLink/pattern_similarity.py
MorphLink/refine_and_merge_util.py
MorphLink/stain_normalization_util.py
MorphLink/tissue_patch_util.py
MorphLink/tissue_seg_util.py
MorphLink/tutorial_util.py
MorphLink/util.py
MorphLink-1.0.3.dist-info/METADATA
MorphLink-1.0.3.dist-info/WHEEL
MorphLink-1.0.3.dist-info/top_level.txt
MorphLink-1.0.3.dist-info/RECORD
