Metadata-Version: 2.1
Name: MorphLink
Version: 1.0.3
Summary: MorphLink: Bridging Cell Morphological Behaviors and Molecular Dynamics in Multi-modal Spatial Omics
Home-page: https://github.com/jianhuupenn/MorphLink
Author: Jing Huang
Author-email: jing.huang@emory.edu
Classifier: Programming Language :: Python :: 3
Classifier: License :: OSI Approved :: MIT License
Classifier: Operating System :: OS Independent
Requires-Python: >=3.6
Requires-Dist: numpy
Requires-Dist: pandas
Requires-Dist: numba
Requires-Dist: anndata
Requires-Dist: scipy
Requires-Dist: scanpy
Requires-Dist: scikit-learn
Requires-Dist: scikit-image
Requires-Dist: matplotlib
Requires-Dist: slideio
Requires-Dist: imutils
Requires-Dist: opencv-python
Requires-Dist: leidenalg
